youtubeless/__init__.py
youtubeless/exceptions.py
youtubeless/types.py
youtubeless/yutubeless.py
youtubeless-1.1.dist-info/WHEEL
youtubeless-1.1.dist-info/METADATA
youtubeless-1.1.dist-info/RECORD
