Metadata-Version: 2.1
Name: youtubeless
Version: 1.1
Summary: Get youtube video information and download links by url!
Home-page: https://github.com/SvineruS/youtubeless
License: UNKNOWN
Author: svinerus
Author-email: svinerus@gmail.com
Requires-Python: >=3.8
